gitlab_mcp/__init__.py
gitlab_mcp/connector.py
gitlab_mcp/count_projects.py
gitlab_mcp/logging_config.py
gitlab_mcp/project_stats.py
gitlab_mcp/server.py
cursor_gitlab_mcp-0.1.15.dist-info/METADATA
cursor_gitlab_mcp-0.1.15.dist-info/WHEEL
cursor_gitlab_mcp-0.1.15.dist-info/entry_points.txt
cursor_gitlab_mcp-0.1.15.dist-info/top_level.txt
cursor_gitlab_mcp-0.1.15.dist-info/RECORD
